{
  "metadata": {
    "generated_at": "2025-08-24T22:22:00.433713",
    "node_count": 10,
    "edge_count": 25,
    "database_info": {
      "filename": "unknown",
      "loaded_at": "",
      "entity_counts": {
        "vehicles": 2,
        "areas": 1,
        "people": 1,
        "militaryUnits": 2,
        "aircraft": 1,
        "weapons": 1,
        "events": 0,
        "organizations": 0,
        "vehicleTypes": 1,
        "areaTypes": 0,
        "peopleTypes": 0,
        "unitTypes": 1,
        "weaponTypes": 0,
        "organizationTypes": 0
      },
      "title": "",
      "description": ""
    },
    "entity_counts": {
      "vehicles": 2,
      "vehicleTypes": 1,
      "people": 1,
      "areas": 1,
      "militaryUnits": 2,
      "unitTypes": 1,
      "aircraft": 1,
      "weapons": 1
    }
  },
  "node_statistics": {
    "total_nodes": 10,
    "node_types": {
      "vehicles": 2,
      "vehicleTypes": 1,
      "people": 1,
      "areas": 1,
      "militaryUnits": 2,
      "unitTypes": 1,
      "aircraft": 1,
      "weapons": 1
    },
    "degree_distribution": {
      "7": 4,
      "2": 2,
      "6": 3,
      "0": 1
    },
    "isolated_nodes": [
      "area-odesa-oblast-001"
    ],
    "degree_stats": {
      "mean": 5.0,
      "median": 6.0,
      "std": 2.4899799195977463,
      "min": 0,
      "max": 7
    }
  },
  "edge_statistics": {
    "total_edges": 25,
    "relationship_types": {
      "vehicleType": 2,
      "co_located": 11,
      "operates_equipment": 8,
      "assigned_to_unit": 2,
      "unitType": 2
    },
    "edge_weight_distribution": {
      "1.0": 25
    }
  },
  "connectivity": {
    "is_connected": false,
    "number_of_components": 2,
    "density": 0.5555555555555556,
    "component_sizes": [
      9,
      1
    ],
    "largest_component_size": 9,
    "average_clustering": 0.8047619047619048,
    "largest_component_avg_path": 1.3333333333333333,
    "largest_component_diameter": 3
  },
  "centrality": {
    "top_degree_centrality": [
      [
        "vehicle-t80-tank-op7-001",
        0.7777777777777777
      ],
      [
        "vehicle-t90-tank-op7-001",
        0.7777777777777777
      ],
      [
        "unit-39th-guards-mrb-op7-001",
        0.7777777777777777
      ],
      [
        "unit-35-gds-mrb-op7-001",
        0.7777777777777777
      ],
      [
        "person-test-001",
        0.6666666666666666
      ],
      [
        "aircraft-test-001",
        0.6666666666666666
      ],
      [
        "weapon-test-001",
        0.6666666666666666
      ],
      [
        "main-battle-tank",
        0.2222222222222222
      ],
      [
        "motor-rifle-brigade",
        0.2222222222222222
      ],
      [
        "area-odesa-oblast-001",
        0.0
      ]
    ],
    "top_betweenness_centrality": [
      [
        "vehicle-t80-tank-op7-001",
        0.08333333333333333
      ],
      [
        "vehicle-t90-tank-op7-001",
        0.08333333333333333
      ],
      [
        "unit-39th-guards-mrb-op7-001",
        0.08333333333333333
      ],
      [
        "unit-35-gds-mrb-op7-001",
        0.08333333333333333
      ],
      [
        "main-battle-tank",
        0.0
      ],
      [
        "person-test-001",
        0.0
      ],
      [
        "area-odesa-oblast-001",
        0.0
      ],
      [
        "motor-rifle-brigade",
        0.0
      ],
      [
        "aircraft-test-001",
        0.0
      ],
      [
        "weapon-test-001",
        0.0
      ]
    ],
    "top_eigenvector_centrality": [
      [
        "vehicle-t80-tank-op7-001",
        0.37945261015861964
      ],
      [
        "vehicle-t90-tank-op7-001",
        0.37945261015861964
      ],
      [
        "unit-39th-guards-mrb-op7-001",
        0.37945261015861964
      ],
      [
        "unit-35-gds-mrb-op7-001",
        0.37945261015861964
      ],
      [
        "person-test-001",
        0.36239199358349244
      ],
      [
        "aircraft-test-001",
        0.36239199358349244
      ],
      [
        "weapon-test-001",
        0.36239199358349244
      ],
      [
        "main-battle-tank",
        0.12263563008968066
      ],
      [
        "motor-rifle-brigade",
        0.12263563008968066
      ],
      [
        "area-odesa-oblast-001",
        4.9215541207517545e-08
      ]
    ]
  },
  "entity_analysis": {
    "countries": {},
    "vehicles": {
      "total_count": 0,
      "by_type": {},
      "by_country": {},
      "by_manufacturer": {},
      "by_decade": {},
      "age_distribution": {}
    },
    "organizations": {
      "total_count": 0,
      "by_type": {},
      "by_country": {},
      "personnel_stats": {}
    },
    "people": {
      "total_count": 0,
      "by_type": {},
      "by_nationality": {},
      "birth_decades": {}
    },
    "areas": {
      "total_count": 0,
      "by_type": {},
      "by_country": {},
      "by_admin_level": {}
    }
  },
  "temporal_analysis": {
    "technology_timeline": {},
    "service_periods": [],
    "modernization_trends": {}
  },
  "geographic_analysis": {
    "country_assets": {},
    "regional_distribution": {},
    "base_locations": {}
  },
  "technology_analysis": {
    "manufacturers": {},
    "technology_generations": {},
    "capability_gaps": {},
    "modernization_patterns": {}
  }
}